Metadata-Version: 2.1
Name: matplotlib-ephys
Version: 0.0.1
Summary: Electrophysiology plotting functions
Home-page: UNKNOWN
License: GNU General Public License
Platform: UNKNOWN
Requires-Python: >=3.6
License-File: LICENSE
